spkly/__init__.py
spkly-0.1.dist-info/LICENSE
spkly-0.1.dist-info/METADATA
spkly-0.1.dist-info/WHEEL
spkly-0.1.dist-info/top_level.txt
spkly-0.1.dist-info/RECORD
